vkbee/__init__.py
vkbee/longpoll.py
vkbee/vkbee.py
vkbee-4.1.dist-info/LICENSE
vkbee-4.1.dist-info/METADATA
vkbee-4.1.dist-info/WHEEL
vkbee-4.1.dist-info/top_level.txt
vkbee-4.1.dist-info/RECORD
